{
  "sectionTitle": "Tools",
  "sectionSubtitle": "Calculators, checklists, and templates.",
  "sectionImage": "assets/cards/full/20260201_2327_Image Generation_remix_01kgekyve4edqbf2rjr12fwh77.png",
  "items": [
    {
      "id": "chlorine-decay",
      "title": "Chlorine Decay Calculator",
      "blurb": "Estimate endpoint residual using residence time and decay constant.",
      "description": "Quick utility for free chlorine forecasting in long detention zones.",
      "thumbnail": "assets/cards/optimized/tools_header.png",
      "tag": "Utility",
      "status": "active",
      "featured": true,
      "url": "#"
    },
    {
      "id": "ct-compliance-sheet",
      "title": "CT Compliance Sheet",
      "blurb": "Daily CT verification helper for disinfection reporting.",
      "description": "Template-based workflow for SWTR reporting and shift handoff checks.",
      "thumbnail": "",
      "tag": "Template",
      "status": "active",
      "featured": true,
      "url": "#"
    },
    {
      "id": "chemical-startup-checklist",
      "title": "Chemical Feed Startup Checklist",
      "blurb": "Step-by-step startup and validation list for feed skids.",
      "description": "Covers pumps, calibration, stroke checks, and residual confirmation.",
      "thumbnail": "assets/cards/optimized/overflow_header.png",
      "tag": "SOP",
      "status": "build",
      "featured": false,
      "url": "#"
    }
  ],
  "_guide": "Each item should include: id, title, blurb, description, tag, status, featured, url. Thumbnail is optional."
}
